test/__init__.py
test/test_ai_api.py
test/test_alert_api.py
test/test_alert_comment_dto.py
test/test_alert_dto.py
test/test_alert_favorite_dto.py
test/test_alert_list_dto.py
test/test_alert_ref_dto.py
test/test_alert_ref_list_dto.py
test/test_alert_ref_result_dto.py
test/test_anomalies_response_dto.py
test/test_create_source_day_dto.py
test/test_create_source_dto.py
test/test_day_api.py
test/test_day_context.py
test/test_day_context_api.py
test/test_day_list_dto.py
test/test_day_model_dto.py
test/test_day_patch_dto.py
test/test_day_trend.py
test/test_day_trend_api.py
test/test_day_trend_input.py
test/test_day_trend_input_list_dto.py
test/test_day_trend_list_dto.py
test/test_days_near_date_result_dto.py
test/test_days_patch_dto.py
test/test_generated_day_context_bulk_dto.py
test/test_generated_day_trend_bulk_dto.py
test/test_import_api.py
test/test_import_day_dto.py
test/test_import_days_dto.py
test/test_login_dto.py
test/test_login_response_dto.py
test/test_model_api.py
test/test_model_dto.py
test/test_model_list_dto.py
test/test_model_patch_dto.py
test/test_model_post_dto.py
test/test_models_patch_dto.py
test/test_models_post_dto.py
test/test_onboarding_api.py
test/test_prevision_api.py
test/test_prevision_apply_group_dto.py
test/test_prevision_apply_group_response_dto.py
test/test_prevision_bulk_save_dto.py
test/test_prevision_bulk_save_result_dto.py
test/test_prevision_dto.py
test/test_prevision_list_dto.py
test/test_prevision_patch_dto.py
test/test_prevision_save_dto.py
test/test_prevision_update_result_dto.py
test/test_recompute_day_models_response_dto.py
test/test_recompute_days_projection_response_dto.py
test/test_recompute_models_response_dto.py
test/test_recompute_source_models_response_dto.py
test/test_request_demo_dto.py
test/test_source_api.py
test/test_source_dto.py
test/test_source_group_api.py
test/test_source_group_create_dto.py
test/test_source_group_dto.py
test/test_source_group_list_dto.py
test/test_source_group_patch_dto.py
timelight_ai_python_api_client-1.0.10.dist-info/LICENSE.txt
timelight_ai_python_api_client-1.0.10.dist-info/METADATA
timelight_ai_python_api_client-1.0.10.dist-info/WHEEL
timelight_ai_python_api_client-1.0.10.dist-info/top_level.txt
timelight_ai_python_api_client-1.0.10.dist-info/RECORD
